01-alu/src/alu.sv
module alu #(
    parameter WIDTH = 8
)(
    input  logic [WIDTH-1:0] a,
    input  logic [WIDTH-1:0] b,
    input  logic [2:0]       op,
    output logic [WIDTH-1:0] result,
    output logic             zero
);

    always_comb begin
        case (op)
            3'b000 : result = a + b;
            3'b001 : result = a - b;
            3'b010 : result = a & b;
            3'b011 : result = a | b;
            3'b100 : result = a ^ b;
            3'b101 : result = ~a;
            3'b110 : result = a << 1;
            3'b111 : result = a >> 1;
            default: result = '0;
        endcase
    end

    assign zero = (result == '0);

endmodule

01-alu/tb/alu_tb.sv
`timescale 1ns/1ps

module alu_tb;

    // Déclaration des signaux
    logic [7:0] a, b;
    logic [2:0] op;
    logic [7:0] result;
    logic       zero;

    // Instanciation de l'ALU
    alu #(.WIDTH(8)) dut (
        .a      (a),
        .b      (b),
        .op     (op),
        .result (result),
        .zero   (zero)
    );

    // Tâche pour afficher le résultat
    task check(
        input [7:0] a_in, b_in,
        input [2:0] op_in,
        input [7:0] expected,
        input string op_name
    );
        a = a_in; b = b_in; op = op_in;
        #10;
        if (result === expected)
            $display("OK  | %s | a=%0d b=%0d | result=%0d", op_name, a_in, b_in, result);
        else
            $display("ERR | %s | a=%0d b=%0d | result=%0d (expected %0d)", op_name, a_in, b_in, result, expected);
    endtask

    // Tests
    initial begin
        $dumpfile("alu_tb.vcd");
        $dumpvars(0, alu_tb);

        $display("=== TEST ALU 8 BITS ===");

        // ADD
        check(8'd10,  8'd20,  3'b000, 8'd30,  "ADD    ");
        check(8'd255, 8'd1,   3'b000, 8'd0,   "ADD OVF");

        // SUB
        check(8'd50,  8'd20,  3'b001, 8'd30,  "SUB    ");
        check(8'd0,   8'd1,   3'b001, 8'd255, "SUB NEG");

        // AND
        check(8'b11001100, 8'b10101010, 3'b010, 8'b10001000, "AND    ");

        // OR
        check(8'b11001100, 8'b10101010, 3'b011, 8'b11101110, "OR     ");

        // XOR
        check(8'b11001100, 8'b10101010, 3'b100, 8'b01100110, "XOR    ");

        // NOT
        check(8'b11001100, 8'd0,        3'b101, 8'b00110011, "NOT    ");

        // SHIFT LEFT
        check(8'b00000011, 8'd0,        3'b110, 8'b00000110, "SHL    ");

        // SHIFT RIGHT
        check(8'b00000110, 8'd0,        3'b111, 8'b00000011, "SHR    ");

        // TEST ZERO FLAG
        check(8'd0, 8'd0, 3'b000, 8'd0, "ZERO   ");
        $display("zero flag = %0b (expected 1)", zero);

        $display("=== FIN DES TESTS ===");
        $finish;
    end

endmodule

01-alu/alu_tb.vcd
$date
	Mon Jul 20 22:30:47 2026
$end
$version
	Icarus Verilog
$end
$timescale
	1ps
$end
$scope module alu_tb $end
$var wire 1 ! zero $end
$var wire 8 " result [7:0] $end
$var reg 8 # a [7:0] $end
$var reg 8 $ b [7:0] $end
$var reg 3 % op [2:0] $end
$scope module dut $end
$var wire 8 & a [7:0] $end
$var wire 8 ' b [7:0] $end
$var wire 3 ( op [2:0] $end
$var wire 1 ! zero $end
$var parameter 32 ) WIDTH $end
$var reg 8 * result [7:0] $end
$upscope $end
$scope task check $end
$var reg 8 + a_in [7:0] $end
$var reg 8 , b_in [7:0] $end
$var reg 8 - expected [7:0] $end
$var reg 3 . op_in [2:0] $end
$upscope $end
$upscope $end
$enddefinitions $end
$comment Show the parameter values. $end
$dumpall
b1000 )
$end
#0
$dumpvars
b0 .
b11110 -
b10100 ,
b1010 +
b11110 *
b0 (
b10100 '
b1010 &
b0 %
b10100 $
b1010 #
b11110 "
0!
$end
#10000
1!
b0 "
b0 *
b1 $
b1 '
b11111111 #
b11111111 &
b0 -
b1 ,
b11111111 +
#20000
0!
b11110 "
b11110 *
b1 %
b1 (
b10100 $
b10100 '
b110010 #
b110010 &
b11110 -
b1 .
b10100 ,
b110010 +
#30000
b11111111 "
b11111111 *
b1 $
b1 '
b0 #
b0 &
b11111111 -
b1 ,
b0 +
#40000
b10001000 "
b10001000 *
b10 %
b10 (
b10101010 $
b10101010 '
b11001100 #
b11001100 &
b10001000 -
b10 .
b10101010 ,
b11001100 +
#50000
b11101110 "
b11101110 *
b11 %
b11 (
b11101110 -
b11 .
#60000
b1100110 "
b1100110 *
b100 %
b100 (
b1100110 -
b100 .
#70000
b110011 "
b110011 *
b101 %
b101 (
b0 $
b0 '
b110011 -
b101 .
b0 ,
#80000
b110 "
b110 *
b110 %
b110 (
b11 #
b11 &
b110 -
b110 .
b11 +
#90000
b11 "
b11 *
b111 %
b111 (
b110 #
b110 &
b11 -
b111 .
b110 +
#100000
1!
b0 "
b0 *
b0 %
b0 (
b0 #
b0 &
b0 -
b0 .
b0 +
